<annotation>
    <folder>data</folder>
    <filename>cjwf3uak3i7790984s2ojsb1j.jpeg</filename>
    <path>/Users/pawel/PycharmProjects/ai-challenge-trees/data/cjwf3uak3i7790984s2ojsb1j.jpeg</path>
    <source>
        <database>Unknown</database>
    </source>
    <size>
        <width>1000</width>
        <height>1000</height>
        <depth>3</depth>
    </size>
    <segmented>0</segmented>
    <object>
        <name>Trees 1</name>
        <pose>Unspecified</pose>
        <truncated>0</truncated>
        <difficult>0</difficult>
        <polygon>
            <x1>17</x1>
                <y1>40</y1>
            <x2>32</x2>
                <y2>47</y2>
            <x3>35</x3>
                <y3>59</y3>
            <x4>23</x4>
                <y4>71</y4>
            <x5>5</x5>
                <y5>70</y5>
            <x6>0</x6>
                <y6>64</y6>
            <x7>0</x7>
                <y7>50</y7>
            </polygon>
        </object>
    <object>
        <name>Trees 1</name>
        <pose>Unspecified</pose>
        <truncated>0</truncated>
        <difficult>0</difficult>
        <polygon>
            <x1>41</x1>
                <y1>40</y1>
            <x2>51</x2>
                <y2>42</y2>
            <x3>51</x3>
                <y3>50</y3>
            <x4>43</x4>
                <y4>53</y4>
            <x5>37</x5>
                <y5>51</y5>
            <x6>35</x6>
                <y6>44</y6>
            </polygon>
        </object>
    </annotation>
